odoo/addons/base_locale_uom_default/README.rst
odoo/addons/base_locale_uom_default/__init__.py
odoo/addons/base_locale_uom_default/__manifest__.py
odoo/addons/base_locale_uom_default/demo/res_lang_demo.xml
odoo/addons/base_locale_uom_default/i18n/ar.po
odoo/addons/base_locale_uom_default/i18n/base_locale_uom_default.pot
odoo/addons/base_locale_uom_default/i18n/ca.po
odoo/addons/base_locale_uom_default/i18n/de.po
odoo/addons/base_locale_uom_default/i18n/es.po
odoo/addons/base_locale_uom_default/i18n/fr.po
odoo/addons/base_locale_uom_default/i18n/hr.po
odoo/addons/base_locale_uom_default/i18n/it.po
odoo/addons/base_locale_uom_default/i18n/nl_NL.po
odoo/addons/base_locale_uom_default/i18n/sl.po
odoo/addons/base_locale_uom_default/i18n/tr.po
odoo/addons/base_locale_uom_default/i18n/zh_CN.po
odoo/addons/base_locale_uom_default/models/__init__.py
odoo/addons/base_locale_uom_default/models/res_lang.py
odoo/addons/base_locale_uom_default/readme/CONFIGURE.rst
odoo/addons/base_locale_uom_default/readme/CONTRIBUTORS.rst
odoo/addons/base_locale_uom_default/readme/DESCRIPTION.rst
odoo/addons/base_locale_uom_default/readme/USAGE.rst
odoo/addons/base_locale_uom_default/static/description/icon.png
odoo/addons/base_locale_uom_default/static/description/index.html
odoo/addons/base_locale_uom_default/tests/__init__.py
odoo/addons/base_locale_uom_default/tests/test_res_lang.py
odoo/addons/base_locale_uom_default/views/res_lang_view.xml
odoo12_addon_base_locale_uom_default-12.0.1.0.1.dist-info/METADATA
odoo12_addon_base_locale_uom_default-12.0.1.0.1.dist-info/WHEEL
odoo12_addon_base_locale_uom_default-12.0.1.0.1.dist-info/top_level.txt
odoo12_addon_base_locale_uom_default-12.0.1.0.1.dist-info/RECORD
