Metadata-Version: 2.1
Name: odoo12-addon-base-locale-uom-default
Version: 12.0.1.0.1
Summary: This provides settings to select default UoMs at the language level.
Home-page: https://github.com/OCA/server-tools
Author: LasLabs, Odoo Community Association (OCA)
Author-email: support@odoo-community.org
License: LGPL-3
Platform: UNKNOWN
Classifier: Programming Language :: Python
Classifier: Framework :: Odoo
Classifier: Framework :: Odoo :: 12.0
Classifier: License :: OSI Approved :: GNU Lesser General Public License v3 (LGPLv3)
Requires-Python: >=3.5
Requires-Dist: odoo <12.1dev,>=12.0a
